LICENSE
MANIFEST.in
README.rst
setup.cfg
setup.py
versioneer.py
tpDcc/__init__.py
tpDcc/dccs/__init__.py
tpDcc/dccs/unreal/__init__.py
tpDcc/dccs/unreal/__logging__.ini
tpDcc/dccs/unreal/__version__.py
tpDcc/dccs/unreal/_version.py
tpDcc/dccs/unreal/dcc.py
tpDcc/dccs/unreal/loader.py
tpDcc/dccs/unreal/core/__init__.py
tpDcc/dccs/unreal/core/asset.py
tpDcc/dccs/unreal/core/controlrig.py
tpDcc/dccs/unreal/core/helpers.py
tpDcc/dccs/unreal/core/skeleton.py
tpDcc/dccs/unreal/ui/__init__.py
tpDcc/dccs/unreal/ui/dialog.py
tpDcc/dccs/unreal/ui/window.py
tpDcc_dccs_unreal.egg-info/PKG-INFO
tpDcc_dccs_unreal.egg-info/SOURCES.txt
tpDcc_dccs_unreal.egg-info/dependency_links.txt
tpDcc_dccs_unreal.egg-info/not-zip-safe
tpDcc_dccs_unreal.egg-info/requires.txt
tpDcc_dccs_unreal.egg-info/top_level.txt