Metadata-Version: 2.1
Name: tpDcc-dccs-unreal
Version: 0.0.1
Summary: Unreal implementation for tpDcc. Utils functions to work with Unreal Python API.
Home-page: https://github.com/tpDcc/tpDcc-dccs-unreal
Author: Tomas Poveda
Author-email: tpovedatd@gmail.com
License: MIT
Platform: UNKNOWN
Provides-Extra: dev
Provides-Extra: test
